wbuilder/__init__.py
wbuilder/jbuilder.py
wbuilder/version.py
wbuilder/wbuilder.py
wbuilder-3.0.5.dist-info/LICENSE
wbuilder-3.0.5.dist-info/METADATA
wbuilder-3.0.5.dist-info/WHEEL
wbuilder-3.0.5.dist-info/top_level.txt
wbuilder-3.0.5.dist-info/RECORD
