Metadata-Version: 2.1
Name: wbuilder
Version: 3.0.5
Summary: HTML template generator for Python.
Home-page: https://github.com/rmaniego/wbuilder
Author: Rodney Maniego Jr.
Author-email: rod.maniego23@gmail.com
License: MIT
Download-URL: https://github.com/rmaniego/wbuilder/archive/v1.0.tar.gz
Keywords: HTML,GENERATOR,PYTHONIC
Platform: UNKNOWN
Classifier: Development Status :: 5 - Production/Stable
Classifier: Intended Audience :: Developers
Classifier: Topic :: Software Development :: Build Tools
Classifier: License :: OSI Approved :: MIT License
Classifier: Programming Language :: Python :: 3
Requires-Python: >=3.6
License-File: LICENSE
Requires-Dist: beautifulsoup4
Requires-Dist: html5lib
Requires-Dist: namari
